Metadata-Version: 2.4
Name: dora_camera_orbbec_v1
Version: 0.0.1
Author-email: Xiang Yang <ryu-yang@qq.com>
Requires-Python: <3.11,>=3.10
License-File: LICENSE
Requires-Dist: dora-rs<0.4.0,>=0.3.11
Requires-Dist: sb-pyorbbecsdk
Requires-Dist: opencv-python
Requires-Dist: numpy<2.0
Provides-Extra: view
Requires-Dist: dora-rs-cli; extra == "view"
Requires-Dist: opencv-plot; extra == "view"
Dynamic: license-file
